whop_sdk/__init__.py
whop_sdk/_base_client.py
whop_sdk/_client.py
whop_sdk/_compat.py
whop_sdk/_constants.py
whop_sdk/_exceptions.py
whop_sdk/_files.py
whop_sdk/_models.py
whop_sdk/_qs.py
whop_sdk/_resource.py
whop_sdk/_response.py
whop_sdk/_streaming.py
whop_sdk/_types.py
whop_sdk/_version.py
whop_sdk/pagination.py
whop_sdk/py.typed
whop_sdk/_utils/__init__.py
whop_sdk/_utils/_compat.py
whop_sdk/_utils/_datetime_parse.py
whop_sdk/_utils/_logs.py
whop_sdk/_utils/_proxy.py
whop_sdk/_utils/_reflection.py
whop_sdk/_utils/_resources_proxy.py
whop_sdk/_utils/_streams.py
whop_sdk/_utils/_sync.py
whop_sdk/_utils/_transform.py
whop_sdk/_utils/_typing.py
whop_sdk/_utils/_utils.py
whop_sdk/lib/.keep
whop_sdk/resources/__init__.py
whop_sdk/resources/access_tokens.py
whop_sdk/resources/account_links.py
whop_sdk/resources/ai_chats.py
whop_sdk/resources/app_builds.py
whop_sdk/resources/apps.py
whop_sdk/resources/authorized_users.py
whop_sdk/resources/chat_channels.py
whop_sdk/resources/checkout_configurations.py
whop_sdk/resources/companies.py
whop_sdk/resources/company_token_transactions.py
whop_sdk/resources/course_chapters.py
whop_sdk/resources/course_lesson_interactions.py
whop_sdk/resources/course_lessons.py
whop_sdk/resources/course_students.py
whop_sdk/resources/courses.py
whop_sdk/resources/disputes.py
whop_sdk/resources/dm_members.py
whop_sdk/resources/entries.py
whop_sdk/resources/experiences.py
whop_sdk/resources/fee_markups.py
whop_sdk/resources/files.py
whop_sdk/resources/forum_posts.py
whop_sdk/resources/forums.py
whop_sdk/resources/invoices.py
whop_sdk/resources/leads.py
whop_sdk/resources/ledger_accounts.py
whop_sdk/resources/members.py
whop_sdk/resources/memberships.py
whop_sdk/resources/messages.py
whop_sdk/resources/notifications.py
whop_sdk/resources/payment_methods.py
whop_sdk/resources/payments.py
whop_sdk/resources/payout_methods.py
whop_sdk/resources/plans.py
whop_sdk/resources/products.py
whop_sdk/resources/promo_codes.py
whop_sdk/resources/reactions.py
whop_sdk-0.0.25.dist-info/METADATA
whop_sdk-0.0.25.dist-info/WHEEL
whop_sdk-0.0.25.dist-info/licenses/LICENSE
whop_sdk-0.0.25.dist-info/RECORD
